flask_simple_crypt.py
Flask_Simple_Crypt-0.3.3.dist-info/LICENSE
Flask_Simple_Crypt-0.3.3.dist-info/METADATA
Flask_Simple_Crypt-0.3.3.dist-info/WHEEL
Flask_Simple_Crypt-0.3.3.dist-info/top_level.txt
Flask_Simple_Crypt-0.3.3.dist-info/RECORD
