Metadata-Version: 2.1
Name: Flask-Simple-Crypt
Version: 0.3.3
Summary: Flask extension based on simple-crypt that allows simple, secure encryption and decryption for Python.
Home-page: https://github.com/furritos/flask-simple-crypt
Author: Carlos Rivas
Author-email: Carlos Rivas <carlos@riv.as>
License: Copyright (c) 2022 Carlos Rivas
Project-URL: Homepage, https://github.com/furritos/flask-simple-crypt
Project-URL: Bug Tracker, https://github.com/furritos/flask-simple-crypt/issues
Platform: any
Classifier: Programming Language :: Python :: 3
Classifier: License :: OSI Approved :: MIT License
Classifier: Operating System :: OS Independent
Classifier: Environment :: Web Environment
Classifier: Intended Audience :: Developers
Classifier: Topic :: Internet :: WWW/HTTP :: Dynamic Content
Classifier: Topic :: Software Development :: Libraries :: Python Modules
Requires-Python: >=3.7
License-File: LICENSE
